y/__init__.py
y/__main__.py
y/yinterpreter.py
y/yreference.py
re_y-2.1.7.dist-info/LICENSE
re_y-2.1.7.dist-info/METADATA
re_y-2.1.7.dist-info/WHEEL
re_y-2.1.7.dist-info/entry_points.txt
re_y-2.1.7.dist-info/RECORD
