Metadata-Version: 2.1
Name: re-y
Version: 2.1.7
Summary: 
License: SSPL-1.0
Author: Philipp Gayret
Author-email: philipp@release-engineers.com
Requires-Python: >=3.11,<4.0
Classifier: License :: Other/Proprietary License
Classifier: Programming Language :: Python :: 3
Classifier: Programming Language :: Python :: 3.11
Requires-Dist: lark (==1.1.5)
Requires-Dist: ruamel.yaml (==0.17.32)
